fixedcal/__init__.py
fixedcal/core/__init__.py
fixedcal/core/date.py
fixedcal/services/leap_days.py
fixedcal-1.0.0.dist-info/LICENSE
fixedcal-1.0.0.dist-info/WHEEL
fixedcal-1.0.0.dist-info/METADATA
fixedcal-1.0.0.dist-info/RECORD
