Metadata-Version: 2.1
Name: fixedcal
Version: 1.0.0
Summary: Fixed calendar package
Home-page: https://github.com/PyryL/fixedcal
License: MIT
Keywords: International Fixed Calendar,IFC,date,datetime
Author: Pyry Lahtinen
Author-email: pyry@pyry.info
Requires-Python: >=3.10,<4.0
Classifier: Intended Audience :: Developers
Classifier: License :: OSI Approved :: MIT License
Classifier: Programming Language :: Python :: 3
Classifier: Programming Language :: Python :: 3.10
Classifier: Programming Language :: Python :: 3.11
Classifier: Topic :: Software Development :: Libraries :: Python Modules
Project-URL: Repository, https://github.com/PyryL/fixedcal
